neural/evaluation.py
neural/functions/activation.py
neural/functions/loss.py
neural/structures/__init__.py
neural/structures/deep_neural_network.py
neural/structures/flat_neural_network.py
neural/structures/neural_network.py
minimalist_neural_networks-1.1.dist-info/LICENSE
minimalist_neural_networks-1.1.dist-info/METADATA
minimalist_neural_networks-1.1.dist-info/WHEEL
minimalist_neural_networks-1.1.dist-info/top_level.txt
minimalist_neural_networks-1.1.dist-info/RECORD
